health_check_wrap/__init__.py
health_check_wrap/main.py
health_check_wrap-1.0.0.dist-info/licenses/LICENSE
health_check_wrap-1.0.0.dist-info/METADATA
health_check_wrap-1.0.0.dist-info/WHEEL
health_check_wrap-1.0.0.dist-info/entry_points.txt
health_check_wrap-1.0.0.dist-info/top_level.txt
health_check_wrap-1.0.0.dist-info/RECORD
