Metadata-Version: 2.4
Name: health-check-wrap
Version: 1.0.0
Summary: A lightweight process supervisor that restarts a service if health checks fail.
Author-email: readwithai <talwrii@gmail.com>
License-Expression: MIT
Keywords: supervision,health-check,systemd,cli
Classifier: Programming Language :: Python :: 3
Classifier: Programming Language :: Python :: 3.9
Classifier: Programming Language :: Python :: 3.10
Classifier: Programming Language :: Python :: 3.11
Requires-Python: >=3.9
License-File: LICENSE
Dynamic: license-file
